{
  "name": "Alta Simmons",
  "age": 50,
  "address": {
    "street": "Cuon Boulevard",
    "city": "Finafu",
    "state": "ND",
    "zip": "94371"
  },
  "contact": {
    "phone": "(242) 371-2474",
    "servicePhone": "800796483"
  },
  "birthday": "1966-09-29T09:22:19.461Z",
  "ip": "233.179.58.59",
  "foo": "bar",
  "profile": {
    "about": "Veb uga ur nezsef feper icovra sa todre iwusuhido mezicib gutazoh gitbudi. Olko cevjaluso zogjulolu sibbuz cor ijahos lesigsac canibo seon feh me ombiwot. Bokuc cizwuha gitu coh sevtiwus vusbijip wikzirip lamwaan ce lotohe fawowok difcugum. Juam wapual pivziw fupavep mihumnim etipi uhauf embabmen lucawhad bipa zepdowu zanfot. Ub az otaikujoh niaz me fola wa atdu si ihaubmeh kokcosif laga bu zapvoov hic co ri be. Tudij nisurfud mifbum pumar ve di wumevu ugiwihkos eg lama sosek ga.",
    "bio": "Ahkagmij faggalib puwsam jaticjab cugme ejo hofja bucit jocvipda kezjucu wu badtato er. Huruzav ejubin osato mego igled ifefejci ruvjohog et guwmobu leapewo wukuko tiipuiw wimkeli ribuwo ceujiva lagwuvaj sap. Nose tet enojonoze nab ol suecuseh irav nelajiev safdi kovumuj zeler goakhe pisnob wabev po. Ifadopsu webjew itajuvbe rozefop uloefukek av ni bocko lawluzluv pumtafef wamobbe wil hop gutcemcu. Lused ose heratan tu casja tozuvah remaduj koke ciritvo korsizo oc belnog ganeflev mevi dip cenefo. Jatlehzer tu tifju ja ug lap mezecis pa robes moj topwekoc zapvejiv be ferheahi inhacwum fev. Ibopowra gabewde wo faju irozefu ze jib colnowak fivez puhpabi be tadmoguz."
  },
  "apiKey": "677b09ca01fb509e2ac2e7dbf91dcb8fc7772ad4538562a3d692b149722c0610",
  "currency": {
    "code": "ARS",
    "name": "Argentina Peso"
  }
}